humanize_rs/__init__.py
humanize_rs/humanize_rs.cpython-38-x86_64-linux-gnu.so
humanize_rs-0.1.1.dist-info/METADATA
humanize_rs-0.1.1.dist-info/WHEEL
humanize_rs-0.1.1.dist-info/RECORD
